mmconfig/__init__.py
mmconfig/mmconfig.py
mmconfig/mmconfig.egg-info/PKG-INFO
mmconfig/mmconfig.egg-info/SOURCES.txt
mmconfig/mmconfig.egg-info/dependency_links.txt
mmconfig/mmconfig.egg-info/top_level.txt
mmconfig-0.0.5.dist-info/METADATA
mmconfig-0.0.5.dist-info/WHEEL
mmconfig-0.0.5.dist-info/top_level.txt
mmconfig-0.0.5.dist-info/RECORD
