Metadata-Version: 2.1
Name: mmconfig
Version: 0.0.5
Summary: Package for viewing mm configs
Home-page: https://github.com/AllentDan/mmconfig
Author: Allent
Author-email: AllentDan@gmail.com
License: Apache License 2.0
Keywords: config
Platform: UNKNOWN
Classifier: Development Status :: 4 - Beta
Classifier: License :: OSI Approved :: Apache Software License
Classifier: Operating System :: OS Independent
Classifier: Programming Language :: Python :: 3
Classifier: Programming Language :: Python :: 3.5
Classifier: Programming Language :: Python :: 3.6
Classifier: Programming Language :: Python :: 3.7
Classifier: Programming Language :: Python :: 3.8
Classifier: Programming Language :: Python :: 3.9
